_oppai.cpython-35m-x86_64-linux-gnu.so
oppai.py
oppaikawata-103.4.2.dist-info/METADATA
oppaikawata-103.4.2.dist-info/WHEEL
oppaikawata-103.4.2.dist-info/top_level.txt
oppaikawata-103.4.2.dist-info/RECORD
