Metadata-Version: 2.1
Name: oppaikawata
Version: 103.4.2
Summary: osu! pp and difficulty calculator, C bindings
Home-page: https://github.com/Francesco149/oppai-ng
Author: Franc[e]sco
Author-email: lolisamurai@tfwno.gf
License: Unlicense
Keywords: osu! osu
Platform: UNKNOWN
Classifier: Programming Language :: Python :: 2
Classifier: Programming Language :: Python :: 3
Classifier: Intended Audience :: Developers
Classifier: License :: Public Domain
Classifier: Topic :: Software Development :: Libraries
Classifier: Topic :: Utilities
